{
  "schema_version": 1,
  "meta": {
    "mode": "lint",
    "track": "quarto",
    "generated_at": "2026-04-27T13:02:27Z",
    "host": {"os": "linux", "arch": "x86_64", "cpu": "AMD Ryzen 9 7900 12-Core Processor", "cores": 24},
    "min_runs": 3,
    "tools": {
      "panache": {"version": "2.39.0"},
      "prettier": {"version": "3.6.2"},
      "rumdl": {"version": "0.1.67"}
    }
  },
  "repos": [
    {"id":"quarto-dev__quarto-web","name":"quarto-dev/quarto-web","file_count":568,"total_bytes":2349853,"extension":"qmd"},
    {"id":"mlr-org__mlr3book","name":"mlr-org/mlr3book","file_count":31,"total_bytes":974193,"extension":"qmd"},
    {"id":"RohanAlexander__tswd","name":"RohanAlexander/tswd","file_count":34,"total_bytes":1475505,"extension":"qmd"},
    {"id":"jolars__panache","name":"jolars/panache","file_count":108,"total_bytes":173620,"extension":"qmd"}
  ],
  "results": [
    {"repo":"quarto-dev__quarto-web","tool":"panache","mean_ms":50.1911,"stddev_ms":1.5766,"min_ms":47.7603,"max_ms":51.7860,"runs":5,"failed":false},
    {"repo":"quarto-dev__quarto-web","tool":"rumdl","mean_ms":59.8688,"stddev_ms":1.8297,"min_ms":57.6538,"max_ms":62.0107,"runs":5,"failed":false},
    {"repo":"mlr-org__mlr3book","tool":"panache","mean_ms":20.8205,"stddev_ms":1.4188,"min_ms":18.5897,"max_ms":25.9385,"runs":53,"failed":false},
    {"repo":"mlr-org__mlr3book","tool":"rumdl","mean_ms":19.6754,"stddev_ms":0.5665,"min_ms":18.7787,"max_ms":21.3012,"runs":53,"failed":false},
    {"repo":"RohanAlexander__tswd","tool":"panache","mean_ms":28.2025,"stddev_ms":2.4308,"min_ms":24.7092,"max_ms":36.3876,"runs":45,"failed":false},
    {"repo":"RohanAlexander__tswd","tool":"rumdl","mean_ms":27.4212,"stddev_ms":2.2519,"min_ms":24.8742,"max_ms":32.1157,"runs":46,"failed":false},
    {"repo":"jolars__panache","tool":"panache","mean_ms":16.2507,"stddev_ms":1.1715,"min_ms":14.8797,"max_ms":19.2266,"runs":23,"failed":false},
    {"repo":"jolars__panache","tool":"rumdl","mean_ms":17.9733,"stddev_ms":0.7210,"min_ms":16.8054,"max_ms":19.8564,"runs":24,"failed":false}
  ]
}
